rdpermute/__init__.py
rdpermute/enums.py
rdpermute/rdpermute.py
rdpermute-0.1.1.dist-info/LICENSE
rdpermute-0.1.1.dist-info/METADATA
rdpermute-0.1.1.dist-info/WHEEL
rdpermute-0.1.1.dist-info/RECORD
