Metadata-Version: 2.1
Name: rdpermute
Version: 0.1.1
Summary: Perform permutation test proposed by Ganong and Jäger (2018) https://www.tandfonline.com/doi/full/10.1080/01621459.2017.1328356
Author: leostimpfle
Author-email: leonardstimpfle@icloud.com
Requires-Python: >=3.12,<4.0
Classifier: Programming Language :: Python :: 3
Classifier: Programming Language :: Python :: 3.12
Requires-Dist: jupyter-console (>=6.6.3,<7.0.0)
Requires-Dist: pytest (>=8.3.4,<9.0.0)
Requires-Dist: rdrobust (>=1.3.0,<2.0.0)
Requires-Dist: stata-setup (>=0.1.3,<0.2.0)
